fs/dlna/__init__.py
fs/dlna/dlnafs.py
fs/dlna/opener.py
fs/dlna/seekable_http_file.py
fs.dlna-0.2.7.dist-info/LICENSE
fs.dlna-0.2.7.dist-info/METADATA
fs.dlna-0.2.7.dist-info/WHEEL
fs.dlna-0.2.7.dist-info/entry_points.txt
fs.dlna-0.2.7.dist-info/top_level.txt
fs.dlna-0.2.7.dist-info/zip-safe
fs.dlna-0.2.7.dist-info/RECORD
