Metadata-Version: 2.1
Name: fs.dlna
Version: 0.2.7
Summary: Youtube Filesystem for PyFilsystem2
Home-page: https://github.com/media-proxy/fs.dlna
Author: Merlin Kessler
Author-email: m3rlink@gmx.de
License: MIT
Keywords: filesystem,Pyfilesystem2,dlna,upnp
Platform: any
Classifier: Development Status :: 4 - Beta
Classifier: Intended Audience :: Developers
Classifier: License :: OSI Approved :: MIT License
Classifier: Operating System :: OS Independent
Classifier: Programming Language :: Python
Classifier: Programming Language :: Python :: 2.7
Classifier: Programming Language :: Python :: 3.4
Classifier: Programming Language :: Python :: 3.5
Classifier: Programming Language :: Python :: 3.6
Classifier: Programming Language :: Python :: 3.7
Classifier: Topic :: Software Development :: Libraries :: Python Modules
Classifier: Topic :: System :: Filesystems
Requires-Python: !=3.0.*,!=3.1.*,!=3.2.*,!=3.3.*,>=2.7
Requires-Dist: fs (~=2.4.11)
Requires-Dist: xmltodict (~=0.12.0)
Requires-Dist: uPnPClient (~=0.0.8)
Requires-Dist: Cython (==0.29.7)
Requires-Dist: netifaces (~=0.10.9)
Provides-Extra: dev
Requires-Dist: docutils (==0.14) ; extra == 'dev'
Requires-Dist: Pygments (==2.3.1) ; extra == 'dev'
Requires-Dist: codecov (==2.0.15) ; extra == 'dev'
Provides-Extra: test
Requires-Dist: green (==2.16.1) ; extra == 'test'
Requires-Dist: coverage (==4.5.3) ; extra == 'test'
Requires-Dist: mock (==2.0.0) ; (python_version < "3.3") and extra == 'test'
